Workbook

Sheet Read Me
A1: SILVERLINE INDUSTRIES LIMITED
A2: Financial Results workbook — Q2 and half year ended 30 September 2026 | fictional illustrative data only
A4: IMPORTANT | B4: This workbook contains entirely fictional data for a fictional company. It is a working model for demonstration only and is not an audited/limited-reviewed statement, an exchange filing, or investment information. Do not file or rely on it without replacing all data and having Finance, the auditor and Company Secretary validate it.
A6: Company | B6: Silverline Industries Limited — fictional listed Indian company.
A7: Reporting period | B7: Quarter and half year ended 30 September 2026 (Q2 / H1 FY 2026–27).
A8: Units | B8: ₹ crore unless specified; per-share figures in ₹; share count in crore shares where indicated.
A9: Workbook structure | B9: Summary dashboard, standalone results, consolidated results, segment information, balance sheet, cash flow, EPS, notes, and filing checklist.
A10: Data status | B10: All figures are invented to provide an internally consistent sample. No real company or security is represented.
A11: Formula use | B11: Totals and selected ratios are formula-driven. Some line items are illustrative assumptions and must be reconciled to actual trial balances and reporting schedules.
A12: Regulatory format | B12: The workbook is a management-style detailed model. It is not a substitute for the prescribed SEBI LODR Regulation 33 results format, XBRL filing, auditor report or stock-exchange templates.
A13: Review controls | B13: Confirm standalone/consolidated perimeter, accounting policies, Ind AS requirements, comparative periods, segment reporting, EPS, tax, cash flow, audit/review report, Board approval, and exchange filing requirements.
A14: No implied approval | B14: Although the earlier fictional Board-meeting sample said results were approved, this workbook remains an illustrative sample and is not evidence of actual approval.

Sheet Dashboard
A1: FINANCIAL RESULTS — DASHBOARD
A2: Illustrative highlights for the quarter and half year ended 30 September 2026 | ₹ crore unless stated
A4: Key metric | B4: Q2 FY27 | C4: Q2 FY26 | D4: YoY change | E4: H1 FY27 | F4: H1 FY26 | G4: YoY change | H4: Comment
A5: Revenue from operations | B5: ='Standalone Results'!B7 | C5: ='Standalone Results'!C7 | D5: =IFERROR(B5/C5-1,0) | E5: ='Standalone Results'!D7 | F5: ='Standalone Results'!E7 | G5: =IFERROR(E5/F5-1,0) | H5: Growth across quarter and half year
A6: Total income | B6: ='Standalone Results'!B10 | C6: ='Standalone Results'!C10 | D6: =IFERROR(B6/C6-1,0) | E6: ='Standalone Results'!D10 | F6: ='Standalone Results'!E10 | G6: =IFERROR(E6/F6-1,0) | H6: Includes other income
A7: Profit before tax | B7: ='Standalone Results'!B20 | C7: ='Standalone Results'!C20 | D7: =IFERROR(B7/C7-1,0) | E7: ='Standalone Results'!D20 | F7: ='Standalone Results'!E20 | G7: =IFERROR(E7/F7-1,0) | H7: Before tax
A8: Profit after tax | B8: ='Standalone Results'!B22 | C8: ='Standalone Results'!C22 | D8: =IFERROR(B8/C8-1,0) | E8: ='Standalone Results'!D22 | F8: ='Standalone Results'!E22 | G8: =IFERROR(E8/F8-1,0) | H8: After tax
A9: PAT margin | B9: =IFERROR(B8/B5,0) | C9: =IFERROR(C8/C5,0) | D9: =B9-C9 | E9: =IFERROR(E8/E5,0) | F9: =IFERROR(F8/F5,0) | G9: =E9-F9 | H9: PAT / revenue
A10: Basic EPS (₹) | B10: ='EPS & Ratios'!B7 | C10: ='EPS & Ratios'!C7 | D10: =IFERROR(B10/C10-1,0) | E10: ='EPS & Ratios'!D7 | F10: ='EPS & Ratios'!E7 | G10: =IFERROR(D10/E10-1,0) | H10: ₹ per equity share
A13: Narrative highlights (illustrative)
A14: • Revenue from operations increased year-on-year in Q2 and H1 in this fictional scenario.
A15: • Profitability improved in the sample data; management commentary would need to be tied to verified operational drivers.
A16: • Segment information, balance sheet, cash flow and EPS tabs provide supporting schedules for review.
A17: • All financial numbers are illustrative and must be replaced with validated company records before use.

Sheet Standalone Results
A1: UNAUDITED STANDALONE FINANCIAL RESULTS
A2: For the quarter and half year ended 30 September 2026 | ₹ crore except EPS
A4: Fictional illustrative figures only — not an Ind AS / stock-exchange filing format
A6: Particulars | B6: Quarter ended 30-Sep-2026 | C6: Quarter ended 30-Sep-2025 | D6: Half year ended 30-Sep-2026 | E6: Half year ended 30-Sep-2025 | F6: Notes / reference
A7: I. Revenue from operations | B7: 1245.6 | C7: 1108.2 | D7: 2430.8 | E7: 2165.4
A8: II. Other income | B8: 18.4 | C8: 15.1 | D8: 35.2 | E8: 29.8
A9: III. Total income (I + II) | B9: =B7+B8 | C9: =C7+C8 | D9: =D7+D8 | E9: =E7+E8 | F9: Formula
A10: IV. Expenses
A11: Cost of materials consumed | B11: 630.5 | C11: 574.1 | D11: 1220 | E11: 1118
A12: Purchases of stock-in-trade | B12: 45 | C12: 41.5 | D12: 90.2 | E12: 82.3
A13: Changes in inventories of finished goods, WIP and stock-in-trade | B13: -8.4 | C13: -5.7 | D13: -15.3 | E13: -9.2 | F13: Negative expense reflects inventory build (illustrative).
A14: Employee benefits expense | B14: 148 | C14: 136.5 | D14: 292 | E14: 268.2
A15: Finance costs | B15: 16.2 | C15: 14.8 | D15: 31.5 | E15: 29.4
A16: Depreciation and amortisation expense | B16: 42.5 | C16: 39 | D16: 83.7 | E16: 77.1
A17: Other expenses | B17: 266.4 | C17: 230.8 | D17: 516.5 | E17: 457.1
A18: Total expenses | B18: =SUM(B11:B17) | C18: =SUM(C11:C17) | D18: =SUM(D11:D17) | E18: =SUM(E11:E17) | F18: Formula
A19: V. Profit before exceptional items and tax | B19: =B9-B18 | C19: =C9-C18 | D19: =D9-D18 | E19: =E9-E18 | F19: Formula
A20: VI. Exceptional items | B20: 0 | C20: 0 | D20: 0 | E20: 0 | F20: Illustrative
A21: VII. Profit before tax | B21: =B19+B20 | C21: =C19+C20 | D21: =D19+D20 | E21: =E19+E20 | F21: Formula
A22: VIII. Tax expense
A23: Current tax | B23: 24 | C23: 20.5 | D23: 45.5 | E23: 39.2
A24: Deferred tax | B24: 3.9 | C24: 3.7 | D24: 7.6 | E24: 6.3
A25: Total tax expense | B25: =SUM(B23:B24) | C25: =SUM(C23:C24) | D25: =SUM(D23:D24) | E25: =SUM(E23:E24) | F25: Formula
A26: IX. Profit for the period | B26: =B21-B25 | C26: =C21-C25 | D26: =D21-D25 | E26: =E21-E25 | F26: Formula
A27: X. Other comprehensive income (net of tax) | B27: 2.1 | C27: 1 | D27: 3.6 | E27: 1.8 | F27: Illustrative
A28: XI. Total comprehensive income | B28: =B26+B27 | C28: =C26+C27 | D28: =D26+D27 | E28: =E26+E27 | F28: Formula
A29: Paid-up equity share capital | B29: 100 | C29: 100 | D29: 100 | E29: 100 | F29: ₹ crore; face value ₹10 per share
A30: Other equity / reserves | B30: [Refer balance sheet] | C30: [Refer balance sheet] | D30: [Refer balance sheet] | E30: [Refer balance sheet] | F30: See Balance Sheet tab
A31: Basic EPS (₹) | B31: ='EPS & Ratios'!B7 | C31: ='EPS & Ratios'!C7 | D31: ='EPS & Ratios'!D7 | E31: ='EPS & Ratios'!E7 | F31: See EPS & Ratios tab
A32: Diluted EPS (₹) | B32: ='EPS & Ratios'!B8 | C32: ='EPS & Ratios'!C8 | D32: ='EPS & Ratios'!D8 | E32: ='EPS & Ratios'!E8 | F32: See EPS & Ratios tab

Sheet Consolidated Results
A1: UNAUDITED CONSOLIDATED FINANCIAL RESULTS
A2: For the quarter and half year ended 30 September 2026 | ₹ crore except EPS
A4: Fictional illustrative figures only — consolidated scope and non-controlling interests are assumptions
A6: Particulars | B6: Quarter ended 30-Sep-2026 | C6: Quarter ended 30-Sep-2025 | D6: Half year ended 30-Sep-2026 | E6: Half year ended 30-Sep-2025 | F6: Notes / reference
A7: I. Revenue from operations | B7: 1378.4 | C7: 1216.7 | D7: 2690.5 | E7: 2381.2
A8: II. Other income | B8: 20.5 | C8: 16.9 | D8: 39.1 | E8: 33
A9: III. Total income (I + II) | B9: =B7+B8 | C9: =C7+C8 | D9: =D7+D8 | E9: =E7+E8 | F9: Formula
A10: IV. Expenses
A11: Cost of materials consumed | B11: 686 | C11: 619.8 | D11: 1328.2 | E11: 1202.5
A12: Purchases of stock-in-trade | B12: 47.5 | C12: 44.2 | D12: 96 | E12: 88.1
A13: Changes in inventories of finished goods, WIP and stock-in-trade | B13: -9 | C13: -6.2 | D13: -16.5 | E13: -10
A14: Employee benefits expense | B14: 164.8 | C14: 151.4 | D14: 326.1 | E14: 298
A15: Finance costs | B15: 19.4 | C15: 17.6 | D15: 37.9 | E15: 34.8
A16: Depreciation and amortisation expense | B16: 49.6 | C16: 45.2 | D16: 98.2 | E16: 89.5
A17: Other expenses | B17: 300.1 | C17: 267 | D17: 583.5 | E17: 523
A18: Total expenses | B18: =SUM(B11:B17) | C18: =SUM(C11:C17) | D18: =SUM(D11:D17) | E18: =SUM(E11:E17) | F18: Formula
A19: V. Profit before exceptional items and tax | B19: =B9-B18 | C19: =C9-C18 | D19: =D9-D18 | E19: =E9-E18 | F19: Formula
A20: VI. Exceptional items | B20: 0 | C20: 0 | D20: 0 | E20: 0 | F20: Illustrative
A21: VII. Profit before tax | B21: =B19+B20 | C21: =C19+C20 | D21: =D19+D20 | E21: =E19+E20 | F21: Formula
A22: VIII. Tax expense
A23: Current tax | B23: 28.4 | C23: 24.1 | D23: 54.2 | E23: 46.8
A24: Deferred tax | B24: 4.4 | C24: 4 | D24: 8.8 | E24: 7
A25: Total tax expense | B25: =SUM(B23:B24) | C25: =SUM(C23:C24) | D25: =SUM(D23:D24) | E25: =SUM(E23:E24) | F25: Formula
A26: IX. Profit for the period | B26: =B21-B25 | C26: =C21-C25 | D26: =D21-D25 | E26: =E21-E25 | F26: Before attribution to NCI
A27: Attributable to owners of the parent | B27: ='EPS & Ratios'!B11 | C27: ='EPS & Ratios'!C11 | D27: ='EPS & Ratios'!D11 | E27: ='EPS & Ratios'!E11
A28: Attributable to non-controlling interests | B28: =B26-B27 | C28: =C26-C27 | D28: =D26-D27 | E28: =E26-E27
A29: X. Other comprehensive income (net of tax) | B29: 2.6 | C29: 1.4 | D29: 4.1 | E29: 2.5
A30: XI. Total comprehensive income | B30: =B26+B29 | C30: =C26+C29 | D30: =D26+D29 | E30: =E26+E29
A31: Paid-up equity share capital | B31: 100 | C31: 100 | D31: 100 | E31: 100 | F31: ₹ crore; face value ₹10 per share
A32: Other equity / reserves | B32: [Refer balance sheet] | C32: [Refer balance sheet] | D32: [Refer balance sheet] | E32: [Refer balance sheet] | F32: See Balance Sheet tab
A33: Basic EPS (₹) | B33: ='EPS & Ratios'!B7 | C33: ='EPS & Ratios'!C7 | D33: ='EPS & Ratios'!D7 | E33: ='EPS & Ratios'!E7
A34: Diluted EPS (₹) | B34: ='EPS & Ratios'!B8 | C34: ='EPS & Ratios'!C8 | D34: ='EPS & Ratios'!D8 | E34: ='EPS & Ratios'!E8

Sheet EPS & Ratios
A1: EPS & SELECTED RATIOS
A2: Illustrative calculations; share count and profit attribution assumptions must be validated
A4: Particulars | B4: Q2 FY27 | C4: Q2 FY26 | D4: H1 FY27 | E4: H1 FY26 | F4: Basis / notes
A5: PAT attributable to equity shareholders (₹ crore) | B5: 76.9 | C5: 67.4 | D5: 143.1 | E5: 125.8 | F5: Standalone illustration; consolidated EPS uses parent attribution in the consolidated results tab.
A6: Weighted average equity shares (crore) | B6: 10 | C6: 10 | D6: 10 | E6: 10 | F6: ₹100 crore paid-up capital / ₹10 face value assumed; confirm weighted average shares.
A7: Basic EPS (₹) | B7: =B5/B6 | C7: =C5/C6 | D7: =D5/D6 | E7: =E5/E6 | F7: PAT attributable / weighted average shares.
A8: Diluted EPS (₹) | B8: =B7 | C8: =C7 | D8: =D7 | E8: =E7 | F8: Assumes no dilutive instruments; verify actual diluted share count.
A9: Revenue from operations (₹ crore) | B9: ='Standalone Results'!B7 | C9: ='Standalone Results'!C7 | D9: ='Standalone Results'!D7 | E9: ='Standalone Results'!E7 | F9: Standalone results.
A10: PAT margin | B10: =B5/B9 | C10: =C5/C9 | D10: =D5/D9 | E10: =E5/E9 | F10: PAT attributable / revenue.
A11: Consolidated PAT attributable to owners (₹ crore) | B11: 82 | C11: 72 | D11: 153 | E11: 133 | F11: Illustrative assumption for EPS; must reconcile to consolidated profit attribution.
A12: Consolidated basic EPS (₹) | B12: =B11/B6 | C12: =C11/C6 | D12: =D11/D6 | E12: =E11/E6 | F12: Consolidated parent-attributable PAT / weighted average shares.
A13: Consolidated diluted EPS (₹) | B13: =B12 | C13: =C12 | D13: =D12 | E13: =E12 | F13: Assumes no dilutive instruments; verify.

Sheet Segment Information
A1: SEGMENT INFORMATION
A2: Illustrative operating segments for quarter and half year ended 30 September 2026 | ₹ crore
A4: Segment | B4: Q2 FY27 Revenue | C4: Q2 FY26 Revenue | D4: H1 FY27 Revenue | E4: H1 FY26 Revenue | F4: Q2 FY27 Segment Result | G4: Notes
A5: Industrial Components | B5: 780 | C5: 698 | D5: 1512 | E5: 1368 | F5: 88 | G5: Fictional reportable segment.
A6: Specialty Materials | B6: 365.6 | C6: 318.2 | D6: 708.8 | E6: 612.4 | F6: 38 | G6: Fictional reportable segment.
A7: Services & Aftermarket | B7: 100 | C7: 92 | D7: 210 | E7: 185 | F7: 11 | G7: Fictional reportable segment.
A8: Total segment revenue | B8: =SUM(B5:B7) | C8: =SUM(C5:C7) | D8: =SUM(D5:D7) | E8: =SUM(E5:E7) | F8: =SUM(F5:F7) | G8: Before eliminations, if any.
A9: Inter-segment eliminations | B9: 0 | C9: 0 | D9: 0 | E9: 0 | F9: 0 | G9: Illustrative; no material eliminations assumed.
A10: Revenue from operations | B10: =B8+B9 | C10: =C8+C9 | D10: =D8+D9 | E10: =E8+E9 | G10: Should reconcile to standalone revenue only if this segment perimeter is standalone.
A11: Unallocated corporate costs | F11: -18.2 | G11: Illustrative.
A12: Finance costs | F12: -16.2 | G12: Refer to financial results.
A13: Profit before tax (illustrative reconciliation) | F13: =F8+F11+F12 | G13: This simplified reconciliation is not a prescribed segment note.

Sheet Balance Sheet
A1: BALANCE SHEET — ILLUSTRATIVE SUMMARY
A2: As at 30 September 2026 and 31 March 2026 | ₹ crore
A4: Particulars | B4: As at 30-Sep-2026 | C4: As at 31-Mar-2026 | D4: Notes / reference
A5: ASSETS
A6: Non-current assets
A7: Property, plant and equipment | B7: 680 | C7: 640 | D7: Illustrative.
A8: Capital work-in-progress | B8: 55 | C8: 42 | D8: Illustrative.
A9: Right-of-use assets | B9: 32 | C9: 34 | D9: Illustrative.
A10: Intangible assets | B10: 24 | C10: 25 | D10: Illustrative.
A11: Investments | B11: 65 | C11: 60 | D11: Illustrative.
A12: Other non-current assets | B12: 38 | C12: 35 | D12: Illustrative.
A13: Total non-current assets | B13: =SUM(B7:B12) | C13: =SUM(C7:C12) | D13: Formula.
A14: Current assets
A15: Inventories | B15: 410 | C15: 390 | D15: Illustrative.
A16: Trade receivables | B16: 325 | C16: 300 | D16: Illustrative.
A17: Cash and cash equivalents | B17: 92 | C17: 88 | D17: Illustrative.
A18: Bank balances other than cash equivalents | B18: 35 | C18: 31 | D18: Illustrative.
A19: Other current assets | B19: 88 | C19: 80 | D19: Illustrative.
A20: Total current assets | B20: =SUM(B15:B19) | C20: =SUM(C15:C19) | D20: Formula.
A21: TOTAL ASSETS | B21: =B13+B20 | C21: =C13+C20 | D21: Formula.
A22: EQUITY AND LIABILITIES
A23: Equity share capital | B23: 100 | C23: 100 | D23: Face value ₹10 per share assumed.
A24: Other equity | B24: 700 | C24: 660 | D24: Illustrative.
A25: Total equity | B25: =SUM(B23:B24) | C25: =SUM(C23:C24) | D25: Formula.
A26: Non-current liabilities
A27: Borrowings | B27: 180 | C27: 200 | D27: Illustrative.
A28: Lease liabilities | B28: 24 | C28: 26 | D28: Illustrative.
A29: Deferred tax liabilities | B29: 48 | C29: 43 | D29: Illustrative.
A30: Other non-current liabilities | B30: 25 | C30: 24 | D30: Illustrative.
A31: Total non-current liabilities | B31: =SUM(B27:B30) | C31: =SUM(C27:C30) | D31: Formula.
A32: Current liabilities
A33: Borrowings | B33: 110 | C33: 115 | D33: Illustrative.
A34: Trade payables | B34: 355 | C34: 320 | D34: Illustrative.
A35: Lease liabilities | B35: 10 | C35: 9 | D35: Illustrative.
A36: Current tax liabilities | B36: 18 | C36: 15 | D36: Illustrative.
A37: Other current liabilities | B37: 110 | C37: 100 | D37: Illustrative.
A38: Total current liabilities | B38: =SUM(B33:B37) | C38: =SUM(C33:C37) | D38: Formula.
A39: TOTAL EQUITY AND LIABILITIES | B39: =B25+B31+B38 | C39: =C25+C31+C38 | D39: Should equal total assets; reconcile before use.
A40: Balance check | B40: =B21-B39 | C40: =C21-C39 | D40: Must be zero after validated input; this fictional sample may require reconciliation.

Sheet Cash Flow
A1: CASH FLOW STATEMENT — ILLUSTRATIVE SUMMARY
A2: For the half year ended 30 September 2026 and comparative period | ₹ crore
A4: Particulars | B4: H1 FY27 | C4: H1 FY26 | D4: Notes / reference
A5: A. Cash flows from operating activities
A6: Profit before tax | B6: 196.2 | C6: 171.3 | D6: Illustrative standalone PBT.
A7: Adjustments for depreciation and amortisation | B7: 83.7 | C7: 77.1 | D7: Illustrative.
A8: Finance costs | B8: 31.5 | C8: 29.4 | D8: Illustrative.
A9: Interest income | B9: -4.2 | C9: -3.8 | D9: Illustrative.
A10: Other non-cash adjustments | B10: 6 | C10: 4.5 | D10: Illustrative.
A11: Operating profit before working capital changes | B11: =SUM(B6:B10) | C11: =SUM(C6:C10) | D11: Formula.
A12: Changes in working capital | B12: -28 | C12: -20 | D12: Illustrative.
A13: Cash generated from operations | B13: =B11+B12 | C13: =C11+C12 | D13: Formula.
A14: Income taxes paid | B14: -41 | C14: -35 | D14: Illustrative.
A15: Net cash from operating activities | B15: =B13+B14 | C15: =C13+C14 | D15: Formula.
A16: B. Cash flows from investing activities
A17: Purchase of PPE and capital work-in-progress | B17: -92 | C17: -68 | D17: Illustrative.
A18: Proceeds from sale of PPE | B18: 2.5 | C18: 1 | D18: Illustrative.
A19: Interest received | B19: 4.2 | C19: 3.8 | D19: Illustrative.
A20: Net cash used in investing activities | B20: =SUM(B17:B19) | C20: =SUM(C17:C19) | D20: Formula.
A21: C. Cash flows from financing activities
A22: Proceeds from borrowings | B22: 20 | C22: 30 | D22: Illustrative.
A23: Repayment of borrowings | B23: -45 | C23: -38 | D23: Illustrative.
A24: Interest paid | B24: -31.5 | C24: -29.4 | D24: Illustrative.
A25: Dividend paid | B25: 0 | C25: 0 | D25: Illustrative; interim dividend timing not reflected here.
A26: Lease payments | B26: -7 | C26: -6.5 | D26: Illustrative.
A27: Net cash used in financing activities | B27: =SUM(B22:B26) | C27: =SUM(C22:C26) | D27: Formula.
A28: Net increase / (decrease) in cash | B28: =B15+B20+B27 | C28: =C15+C20+C27 | D28: Formula.
A29: Opening cash and cash equivalents | B29: 88 | C29: 76 | D29: Illustrative.
A30: Closing cash and cash equivalents | B30: =B28+B29 | C30: =C28+C29 | D30: Should reconcile to balance sheet cash; investigate any difference.

Sheet Notes to Results
A1: NOTES TO FINANCIAL RESULTS
A2: Illustrative notes to accompany the management results workbook; all narrative is fictional
A4: Note | B4: Topic | C4: Illustrative disclosure / explanation | D4: Owner / source
A5: 1 | B5: Basis of preparation | C5: These illustrative unaudited standalone financial results have been prepared for demonstration purposes only. Actual results should be prepared under applicable Indian Accounting Standards (Ind AS), the Companies Act, 2013 and relevant SEBI LODR requirements, as applicable. | D5: Finance / Controller
A6: 2 | B6: Reporting entity | C6: Silverline Industries Limited is a fictional Indian industrial company. The workbook assumes a 30 September 2026 reporting date and comparative periods ending 30 September 2025. | D6: Company Secretary / Finance
A7: 3 | B7: Accounting policies | C7: No actual accounting policy elections or estimates are represented. A real filing should include material accounting policy information and disclosures required by applicable standards and regulations. | D7: Finance / Auditor
A8: 4 | B8: Segment reporting | C8: The segment schedule uses three illustrative segments. Actual operating segments should be identified based on the chief operating decision maker’s review and the applicable reporting framework. | D8: Finance
A9: 5 | B9: Related parties | C9: Any actual related-party disclosures should be based on verified relationships, transactions, balances, terms and applicable disclosure requirements. | D9: Finance / Legal
A10: 6 | B10: Exceptional items | C10: No exceptional items are assumed in the sample periods. Actual events must be assessed and disclosed according to applicable standards and requirements. | D10: Finance / Legal
A11: 7 | B11: Contingent liabilities and commitments | C11: No amount is populated in this sample. Actual disclosure should be sourced from legal, tax, treasury and operating teams and reconciled to the financial statements. | D11: Finance / Legal
A12: 8 | B12: Dividend | C12: The earlier fictional Board sample stated an interim dividend of ₹1.50 per equity share. This workbook does not evidence an actual declaration or calculate actual dividend payable; use only after verifying approved records. | D12: Company Secretary / Finance
A13: 9 | B13: Capital expenditure | C13: The earlier fictional Board sample included a capex envelope of up to ₹48 crore. Actual commitments, additions to PPE, CWIP and cash flows must be separately reconciled. | D13: Finance / COO
A14: 10 | B14: Auditor’s review | C14: No auditor’s report is included in this workbook. A real filing should include the signed limited review report / audit report as required and reproduce any qualifications or emphasis-of-matter accurately. | D14: Statutory auditor
A15: 11 | B15: EPS | C15: EPS formulas assume weighted-average shares of 10 crore and no dilutive instruments. Actual EPS must be calculated using the applicable standard and verified share data. | D15: Finance
A16: 12 | B16: Subsequent events | C16: Assess events after the reporting period through the date the financial statements are approved, and disclose as required by the applicable reporting framework. | D16: Finance / Legal

Sheet Filing Checklist
A1: FINANCIAL RESULTS — REVIEW & FILING CHECKLIST
A2: Control checklist for Finance, auditor and Company Secretary review before any real filing
A4: Control ID | B4: Check | C4: Evidence / source | D4: Owner | E4: Status | F4: Reviewer comments
A5: FR-01 | B5: Confirm legal entity, CIN, exchange symbols and reporting perimeter. | C5: Company master / exchange records | D5: Company Secretary | E5: Not started
A6: FR-02 | B6: Reconcile trial balance and financial statement schedules to the general ledger. | C6: Final TB and lead schedules | D6: Finance Controller | E6: Not started
A7: FR-03 | B7: Verify comparative periods, reporting dates and units. | C7: Approved reporting calendar | D7: Finance Controller | E7: Not started
A8: FR-04 | B8: Confirm standalone and consolidated statements and consolidation adjustments. | C8: Consolidation pack / subsidiary reporting | D8: Group Finance | E8: Not started
A9: FR-05 | B9: Verify total income, expenses, PBT, tax, PAT, OCI and total comprehensive income. | C9: Financial statement workings | D9: Finance Controller | E9: Not started
A10: FR-06 | B10: Reconcile segment information and related disclosures to actual operating segments. | C10: Segment reporting pack | D10: Finance / Business Heads | E10: Not started
A11: FR-07 | B11: Verify balance sheet totals, classification and comparative balances. | C11: Balance sheet reconciliations | D11: Finance Controller | E11: Not started
A12: FR-08 | B12: Reconcile cash flow statement to cash balances and cash flow working papers. | C12: Cash flow workings / bank reconciliations | D12: Treasury / Finance | E12: Not started
A13: FR-09 | B13: Recalculate basic and diluted EPS using applicable standard and weighted-average shares. | C13: Share register / EPS calculation | D13: Finance Controller | E13: Not started
A14: FR-10 | B14: Complete related-party, contingent liability, commitments and subsequent-event assessments. | C14: Legal, tax, treasury and RPT registers | D14: Finance / Legal | E14: Not started
A15: FR-11 | B15: Obtain Audit Committee review / recommendation, where applicable. | C15: Committee minutes / recommendation | D15: Company Secretary | E15: Not started
A16: FR-12 | B16: Obtain signed limited review / audit report and reflect report wording accurately. | C16: Signed auditor report | D16: Statutory auditor | E16: Not started
... A21: FR-17 | B21: Remove fictional labels, placeholders and all unverified figures from actual filing pack. | C21: Final proofread version | D21: Independent reviewer | E21: Not started
